dp_transformers/__init__.py
dp_transformers/arguments.py
dp_transformers/dp_utils.py
dp_transformers/module_modification.py
dp_transformers/sampler.py
dp_transformers/grad_sample/__init__.py
dp_transformers/grad_sample/lora/__init__.py
dp_transformers/grad_sample/lora/lora_layer.py
dp_transformers/grad_sample/transformers/__init__.py
dp_transformers/grad_sample/transformers/conv_1d.py
dp_transformers/grad_sample/transformers/tied_embedding.py
dp_transformers/layers/__init__.py
dp_transformers/layers/dp_merged_linear.py
dp_transformers-1.0.0.dist-info/LICENSE.txt
dp_transformers-1.0.0.dist-info/METADATA
dp_transformers-1.0.0.dist-info/WHEEL
dp_transformers-1.0.0.dist-info/top_level.txt
dp_transformers-1.0.0.dist-info/RECORD
