Metadata-Version: 2.1
Name: dp-transformers
Version: 1.0.0
Summary: Differentially-private transformers using HuggingFace and Opacus
Home-page: https://www.github.com/microsoft/dp-transformers
Author: Microsoft
Requires-Python: >=3.7.0
License-File: LICENSE.txt
Requires-Dist: transformers (>=4.20.1)
Requires-Dist: datasets (>=2.0.0)
Requires-Dist: opacus (>=1.2.0)
Requires-Dist: prv-accountant (<0.2.0)
Requires-Dist: torch (<=1.12.1,>=1.9.1)
Provides-Extra: test
Requires-Dist: pytest ; extra == 'test'
Requires-Dist: loralib ; extra == 'test'
